Workbook

Sheet Taxes
A1: State | B1: Gas Tax (cents per gallon) | C1: Sales tax | D1: Income Tax | G1: State Initials | H1: State
A2: Alabama | B2: 28.84 | C2: 0.04 | D2: 0.05 | G2: AL | H2: Alabama
A3: Alaska | B3: 9.95 | C3: 0 | D3: 0 | G3: AK | H3: Alaska
A4: Arizona | B4: 18 | C4: 0.056 | D4: 0.025 | G4: AZ | H4: Arizona
A5: Arkansas | B5: 24.8 | C5: 0.065 | D5: 0.044 | G5: AR | H5: Arkansas
A6: California | B6: 51.1 | C6: 0.06 | D6: 0.133 | G6: CA | H6: California
A7: Colorado | B7: 22 | C7: 0.029 | D7: 0.0455 | G7: CO | H7: Colorado
A8: Connecticut | B8: 37.4 | C8: 0.0635 | D8: 0.0699 | G8: CT | H8: Connecticut
A9: Delaware | B9: 23 | C9: 0 | D9: 0 | G9: DE | H9: Delaware
A10: Florida | B10: 19 | C10: 0.06 | D10: 0 | G10: FL | H10: Florida
A11: Georgia | B11: 31.1 | C11: 0.04 | D11: 0.0549 | G11: GA | H11: Georgia
A12: Hawaii | B12: 16 | C12: 0.04 | D12: 0.11 | G12: HI | H12: Hawaii
A13: Idaho | B13: 33 | C13: 0.06 | D13: 0.06 | G13: ID | H13: Idaho
... A51: Wyoming | B51: 24 | C51: 0.04 | D51: 0.04 | G51: WY | H51: Wyoming

Sheet Orders
A1: Column1 | B1: Column2 | C1: Column3 | D1: Column4 | E1: Column5 | F1: Column6 | G1: Column7 | H1: Column8 | I1: Column9 | J1: Column10 | K1: Column11 | L1: Column12 | M1: Column13 | N1: Column14 | O1: Column15 | P1: Column16 | Q1: Column17 | R1: Column18 | S1: Column19 | V1: Inventory Id | W1: Phone case model
A2: Inventory ID | B2: Phone Case Model | C2: Order ID | D2: Quantity | E2: Price per Case | F2: Subtotal | G2: Customer First Name | H2: Customer Last Name | I2: Street Address | J2: City | K2: State | L2: State lookup | M2: Sales Tax | N2: Shipping | O2: Total | R2: State Initials | S2: State | V2: 2305437589 | W2: Google Pixel 7 Case
A3: 2305437589 | B3: =VLOOKUP(A3, $V$2:$W$6, 2, FALSE) -> Google Pixel 7 Case | C3: 9829 | D3: 1 | E3: 16.16 | F3: 16.16 | G3: Adam | H3: Phillips | I3: 993 Nathan Ford Apt. 764 | J3: Davilaland | K3: OH | L3: =VLOOKUP(K3, $R$3:$S$52, 2, FALSE) -> Ohio | M3: =VLOOKUP(L3, Taxes!$A$2:$D$51, 3, FALSE) -> 0.0575 | N3: =IF(F3>35, 0, 6) -> 6 | O3: =SUM(Orders!F3+(Orders!M3*Orders!F3)+Orders!N3) -> 23.0892 | R3: AL | S3: Alabama | V3: 2325437575 | W3: Samsung Galaxy S22 Case
A4: 2325437575 | B4: =VLOOKUP(A4, $V$2:$W$6, 2, FALSE) -> Samsung Galaxy S22 Case | C4: 6642 | D4: 2 | E4: 24.81 | F4: 49.62 | G4: Lindsey | H4: Anderson | I4: 1300 Kathleen Walk Suite 413 | J4: New Teresa | K4: CT | L4: =VLOOKUP(K4, $R$3:$S$52, 2, FALSE) -> Connecticut | M4: =VLOOKUP(L4, Taxes!$A$2:$D$51, 3, FALSE) -> 0.0635 | N4: =IF(F4>35, 0, 6) -> 0 | O4: =SUM(Orders!F4+(Orders!M4*Orders!F4)+Orders!N4) -> 52.77087 | R4: AK | S4: Alaska | V4: 23405437588 | W4: iPhone 13 Case
A5: 2305437589 | B5: =VLOOKUP(A5, $V$2:$W$6, 2, FALSE) -> Google Pixel 7 Case | C5: 8801 | D5: 3 | E5: 23.42 | F5: 70.26 | G5: Christopher | H5: Sanders | I5: 3980 May Shores | J5: North Matthew | K5: ID | L5: =VLOOKUP(K5, $R$3:$S$52, 2, FALSE) -> Idaho | M5: =VLOOKUP(L5, Taxes!$A$2:$D$51, 3, FALSE) -> 0.06 | N5: =IF(F5>35, 0, 6) -> 0 | O5: =SUM(Orders!F5+(Orders!M5*Orders!F5)+Orders!N5) -> 74.4756 | R5: AZ | S5: Arizona | V5: 23505437598 | W5: OnePlus 11 Case
A6: 23405437588 | B6: =VLOOKUP(A6, $V$2:$W$6, 2, FALSE) -> iPhone 13 Case | C6: 4920 | D6: 5 | E6: 13.47 | F6: 67.35 | G6: Jason | H6: Wong | I6: 6018 Elliott Parkway Suite 599 | J6: Lake Leslietown | K6: MS | L6: =VLOOKUP(K6, $R$3:$S$52, 2, FALSE) -> Mississippi | M6: =VLOOKUP(L6, Taxes!$A$2:$D$51, 3, FALSE) -> 0.07 | N6: =IF(F6>35, 0, 6) -> 0 | O6: =SUM(Orders!F6+(Orders!M6*Orders!F6)+Orders!N6) -> 72.0645 | R6: AR | S6: Arkansas | V6: 21298732309 | W6: iPhone 14 Case
A7: 2325437575 | B7: =VLOOKUP(A7, $V$2:$W$6, 2, FALSE) -> Samsung Galaxy S22 Case | C7: 2855 | D7: 3 | E7: 23.91 | F7: 71.73 | G7: Alex | H7: Allen | I7: 8172 Elizabeth Plains | J7: Port Michellemouth | K7: NJ | L7: =VLOOKUP(K7, $R$3:$S$52, 2, FALSE) -> New Jersey | M7: =VLOOKUP(L7, Taxes!$A$2:$D$51, 3, FALSE) -> 0.06625 | N7: =IF(F7>35, 0, 6) -> 0 | O7: =SUM(Orders!F7+(Orders!M7*Orders!F7)+Orders!N7) -> 76.482112 | R7: CA | S7: California
A8: 2305437589 | B8: =VLOOKUP(A8, $V$2:$W$6, 2, FALSE) -> Google Pixel 7 Case | C8: 4562 | D8: 1 | E8: 21.68 | F8: 21.68 | G8: Anita | H8: Tran | I8: 975 Christopher Estate Suite 151 | J8: Jonesshire | K8: KY | L8: =VLOOKUP(K8, $R$3:$S$52, 2, FALSE) -> Kentucky | M8: =VLOOKUP(L8, Taxes!$A$2:$D$51, 3, FALSE) -> 0.06 | N8: =IF(F8>35, 0, 6) -> 6 | O8: =SUM(Orders!F8+(Orders!M8*Orders!F8)+Orders!N8) -> 28.9808 | R8: CO | S8: Colorado
A9: 23405437588 | B9: =VLOOKUP(A9, $V$2:$W$6, 2, FALSE) -> iPhone 13 Case | C9: 1524 | D9: 2 | E9: 11.35 | F9: 22.7 | G9: Austin | H9: Beasley | I9: 78607 Castillo Trafficway | J9: Port Jenniferfurt | K9: VT | L9: =VLOOKUP(K9, $R$3:$S$52, 2, FALSE) -> Vermont | M9: =VLOOKUP(L9, Taxes!$A$2:$D$51, 3, FALSE) -> 0.06 | N9: =IF(F9>35, 0, 6) -> 6 | O9: =SUM(Orders!F9+(Orders!M9*Orders!F9)+Orders!N9) -> 30.062 | R9: CT | S9: Connecticut
A10: 2325437575 | B10: =VLOOKUP(A10, $V$2:$W$6, 2, FALSE) -> Samsung Galaxy S22 Case | C10: 2994 | D10: 2 | E10: 13.54 | F10: 27.08 | G10: Nicholas | H10: Vazquez | I10: 693 Morrison Estates Apt. 101 | J10: Port Megan | K10: MS | L10: =VLOOKUP(K10, $R$3:$S$52, 2, FALSE) -> Mississippi | M10: =VLOOKUP(L10, Taxes!$A$2:$D$51, 3, FALSE) -> 0.07 | N10: =IF(F10>35, 0, 6) -> 6 | O10: =SUM(Orders!F10+(Orders!M10*Orders!F10)+Orders!N10) -> 34.9756 | R10: DE | S10: Delaware
A11: 2325437575 | B11: =VLOOKUP(A11, $V$2:$W$6, 2, FALSE) -> Samsung Galaxy S22 Case | C11: 7096 | D11: 5 | E11: 14.88 | F11: 74.4 | G11: Jeff | H11: Kirby | I11: 752 Ramirez Knoll | J11: Joannaview | K11: TN | L11: =VLOOKUP(K11, $R$3:$S$52, 2, FALSE) -> Tennessee | M11: =VLOOKUP(L11, Taxes!$A$2:$D$51, 3, FALSE) -> 0.07 | N11: =IF(F11>35, 0, 6) -> 0 | O11: =SUM(Orders!F11+(Orders!M11*Orders!F11)+Orders!N11) -> 79.608 | R11: FL | S11: Florida
A12: 23405437588 | B12: =VLOOKUP(A12, $V$2:$W$6, 2, FALSE) -> iPhone 13 Case | C12: 7388 | D12: 1 | E12: 15.63 | F12: 15.63 | G12: Jasmine | H12: Long | I12: 280 Cox Turnpike | J12: South Masonstad | K12: UT | L12: =VLOOKUP(K12, $R$3:$S$52, 2, FALSE) -> Utah | M12: =VLOOKUP(L12, Taxes!$A$2:$D$51, 3, FALSE) -> 0.0485 | N12: =IF(F12>35, 0, 6) -> 6 | O12: =SUM(Orders!F12+(Orders!M12*Orders!F12)+Orders!N12) -> 22.388055 | R12: GA | S12: Georgia
A13: 23405437588 | B13: =VLOOKUP(A13, $V$2:$W$6, 2, FALSE) -> iPhone 13 Case | C13: 8427 | D13: 5 | E13: 10.84 | F13: 54.2 | G13: Kimberly | H13: Murray | I13: 5355 Villanueva Manors Apt. 147 | J13: Brandonborough | K13: TN | L13: =VLOOKUP(K13, $R$3:$S$52, 2, FALSE) -> Tennessee | M13: =VLOOKUP(L13, Taxes!$A$2:$D$51, 3, FALSE) -> 0.07 | N13: =IF(F13>35, 0, 6) -> 0 | O13: =SUM(Orders!F13+(Orders!M13*Orders!F13)+Orders!N13) -> 57.994 | R13: HI | S13: Hawaii
A14: 23405437588 | B14: =VLOOKUP(A14, $V$2:$W$6, 2, FALSE) -> iPhone 13 Case | C14: 4290 | D14: 5 | E14: 20.7 | F14: 103.5 | G14: Cameron | H14: Smith | I14: 6420 Werner Heights | J14: Hernandezbury | K14: NM | L14: =VLOOKUP(K14, $R$3:$S$52, 2, FALSE) -> New Mexico | M14: =VLOOKUP(L14, Taxes!$A$2:$D$51, 3, FALSE) -> 0.04875 | N14: =IF(F14>35, 0, 6) -> 0 | O14: =SUM(Orders!F14+(Orders!M14*Orders!F14)+Orders!N14) -> 108.54563 | R14: ID | S14: Idaho
A15: 23405437588 | B15: =VLOOKUP(A15, $V$2:$W$6, 2, FALSE) -> iPhone 13 Case | C15: 2203 | D15: 3 | E15: 22.18 | F15: 66.54 | G15: Richard | H15: Smith | I15: 75379 Ruiz Ridge Suite 952 | J15: New Jamestown | K15: MA | L15: =VLOOKUP(K15, $R$3:$S$52, 2, FALSE) -> Massachusetts | M15: =VLOOKUP(L15, Taxes!$A$2:$D$51, 3, FALSE) -> 0.0625 | N15: =IF(F15>35, 0, 6) -> 0 | O15: =SUM(Orders!F15+(Orders!M15*Orders!F15)+Orders!N15) -> 70.69875 | R15: IL | S15: Illinois
A16: 2305437589 | B16: =VLOOKUP(A16, $V$2:$W$6, 2, FALSE) -> Google Pixel 7 Case | C16: 8401 | D16: 2 | E16: 17.57 | F16: 35.14 | G16: Christine | H16: Hanson | I16: 125 Chang Locks | J16: Davisborough | K16: MN | L16: =VLOOKUP(K16, $R$3:$S$52, 2, FALSE) -> Minnesota | M16: =VLOOKUP(L16, Taxes!$A$2:$D$51, 3, FALSE) -> 0.06875 | N16: =IF(F16>35, 0, 6) -> 0 | O16: =SUM(Orders!F16+(Orders!M16*Orders!F16)+Orders!N16) -> 37.555875 | R16: IN | S16: Indiana
A17: 23505437598 | B17: =VLOOKUP(A17, $V$2:$W$6, 2, FALSE) -> OnePlus 11 Case | C17: 4055 | D17: 1 | E17: 21.66 | F17: 21.66 | G17: Stephen | H17: Bowman | I17: 22570 Gonzales Mission Apt. 526 | J17: South Barry | K17: IN | L17: =VLOOKUP(K17, $R$3:$S$52, 2, FALSE) -> Indiana | M17: =VLOOKUP(L17, Taxes!$A$2:$D$51, 3, FALSE) -> 0.07 | N17: =IF(F17>35, 0, 6) -> 6 | O17: =SUM(Orders!F17+(Orders!M17*Orders!F17)+Orders!N17) -> 29.1762 | R17: IA | S17: Iowa
A18: 21298732309 | B18: =VLOOKUP(A18, $V$2:$W$6, 2, FALSE) -> iPhone 14 Case | C18: 4384 | D18: 3 | E18: 19.52 | F18: 58.56 | G18: Lisa | H18: Clark | I18: 4425 Jennifer Roads | J18: Hallborough | K18: IN | L18: =VLOOKUP(K18, $R$3:$S$52, 2, FALSE) -> Indiana | M18: =VLOOKUP(L18, Taxes!$A$2:$D$51, 3, FALSE) -> 0.07 | N18: =IF(F18>35, 0, 6) -> 0 | O18: =SUM(Orders!F18+(Orders!M18*Orders!F18)+Orders!N18) -> 62.6592 | R18: KS | S18: Kansas
... A52: 2325437575 | B52: =VLOOKUP(A52, $V$2:$W$6, 2, FALSE) -> Samsung Galaxy S22 Case | C52: 5074 | D52: 3 | E52: 20.14 | F52: 60.42 | G52: Mark | H52: Nelson | I52: 716 David Divide Suite 484 | J52: Port Sergio | K52: RI | L52: =VLOOKUP(K52, $R$3:$S$52, 2, FALSE) -> Rhode Island | M52: =VLOOKUP(L52, Taxes!$A$2:$D$51, 3, FALSE) -> 0.07 | N52: =IF(F52>35, 0, 6) -> 0 | O52: =SUM(Orders!F52+(Orders!M52*Orders!F52)+Orders!N52) -> 64.6494 | R52: WY | S52: Wyoming
A53: Total | E53: =SUBTOTAL(101,Table2[Column5]) -> 18.1184 | F53: =SUBTOTAL(101,Table2[Column6]) -> 54.6482 | S53: =SUBTOTAL(103,Table2[Column19]) -> 51
B56: Average Subtotal | C56: 18.12
B57: How many customers are above average subtotal? | C57: =COUNTIF(E3:E52, ">18.12") -> 27
B58: Which state has the most orders? | C58: Minnesota, Tennessee

Sheet Charts
A3: Row Labels | B3: Count of Column3
A4: CT | B4: 1
A5: MA | B5: 1
A6: ME | B6: 1
A7: NH | B7: 2
A8: NJ | B8: 1
A9: PA | B9: 1
A10: Grand Total | B10: 7
B42: Minnesota, Tennessee
